tap_fedidb/__init__.py
tap_fedidb/__main__.py
tap_fedidb-0.5.1.dist-info/METADATA
tap_fedidb-0.5.1.dist-info/WHEEL
tap_fedidb-0.5.1.dist-info/entry_points.txt
tap_fedidb-0.5.1.dist-info/licenses/LICENSE
tap_fedidb-0.5.1.dist-info/RECORD
