Metadata-Version: 2.4
Name: tap-fedidb
Version: 0.5.1
Summary: Singer tap for FediDB, built with the Meltano SDK for Singer Taps.
Project-URL: Documentation, https://github.com/reservoir-data/tap-fedidb#readme
Project-URL: Homepage, https://github.com/reservoir-data/tap-fedidb
Project-URL: Repository, https://github.com/reservoir-data/tap-fedidb
Author-email: Edgar Ramírez-Mondragón <edgarrmondragon@hey.com>
Maintainer-email: Edgar Ramírez-Mondragón <edgarrmondragon@hey.com>
License-Expression: Apache-2.0
License-File: LICENSE
Keywords: ELT,FediDB,singer.io
Classifier: Programming Language :: Python :: 3 :: Only
Classifier: Programming Language :: Python :: 3.10
Classifier: Programming Language :: Python :: 3.11
Classifier: Programming Language :: Python :: 3.12
Classifier: Programming Language :: Python :: 3.13
Classifier: Programming Language :: Python :: 3.14
Requires-Python: >=3.10
Requires-Dist: singer-sdk~=0.51.0
Requires-Dist: typing-extensions>=4.15; python_full_version < '3.12'
